pointevector/zip/__init__.py
pointevector/zip/_central_directory_header.py
pointevector/zip/_compression.py
pointevector/zip/_data_descriptor.py
pointevector/zip/_eocd.py
pointevector/zip/_flags.py
pointevector/zip/_local_header.py
pointevector/zip/_zip64_eocd.py
pointevector/zip/_zip64_eocd_locator.py
pointevector/zip/exceptions.py
pointevector/zip/parser.py
pointevector_zip-0.0.3.dist-info/LICENSE
pointevector_zip-0.0.3.dist-info/METADATA
pointevector_zip-0.0.3.dist-info/WHEEL
pointevector_zip-0.0.3.dist-info/top_level.txt
pointevector_zip-0.0.3.dist-info/RECORD
