Metadata-Version: 2.1
Name: pointevector-zip
Version: 0.0.3
Home-page: https://github.com/Pointe-Vector/zip
Author: Andrew Hoekstra
Author-email: andrew@pointevector.com
License-File: LICENSE
